AUTHORS.rst
CHANGELOG.rst
CONTRIBUTING.rst
LICENSE
MANIFEST.in
README.rst
pyproject.toml
setup.cfg
setup.py
docs/Makefile
docs/htm.geometry.rst
docs/htm.rst
docs/make.bat
docs/modules.rst
docs/source/acknowledgements.rst
docs/source/authors.rst
docs/source/changelog.rst
docs/source/conf.py
docs/source/contributing.rst
docs/source/index.rst
docs/source/installation.rst
docs/source/license.rst
docs/source/readme.rst
docs/source/tutorial.rst
docs/source/usage.rst
docs/source/tutorial/htm.rst
htm/__init__.py
htm/constants.py
htm/intersection.py
htm/node.py
htm/geometry/__init__.py
htm/geometry/halfspace.py
htm/geometry/relationships.py
htm/geometry/vector.py
pyhtm.egg-info/PKG-INFO
pyhtm.egg-info/SOURCES.txt
pyhtm.egg-info/dependency_links.txt
pyhtm.egg-info/not-zip-safe
pyhtm.egg-info/top_level.txt
tests/results.txt
tests/test_htm.py
tests/test_trixel.py
tests/test_vector.py
tests/data/959911071872_trixel.p
tests/data/database_alerts_errors.csv
tests/data/database_alerts_wrong.csv
tests/data/htm_ids.p
tests/data/htm_ranges.p
tests/data/issue-1-halfspace.p
tests/data/issue-1-parent.p
tests/data/test_out.csv
tests/data/AN-455/halfspace.p
tests/data/AN-455/node.p