Metadata-Version: 1.1
Name: pyhtm
Version: 0.1.5
Summary: Utilities for working with Hierarchical Triangular Meshes (HTMs).
Home-page: https://gitlab.com/noao/antares/htm
Author: Nicholas Wolf
Author-email: nwolf@noao.edu
License: MIT license
Keywords: htm
Platform: UNKNOWN
Classifier: Development Status :: 2 - Pre-Alpha
Classifier: Intended Audience :: Developers
Classifier: License :: OSI Approved :: MIT License
Classifier: Natural Language :: English
Classifier: Programming Language :: Python :: 3
Classifier: Programming Language :: Python :: 3.5
Classifier: Programming Language :: Python :: 3.6
Classifier: Programming Language :: Python :: 3.7
Classifier: Programming Language :: Python :: 3.8
